weatherify/__init__.py
weatherify/weatherify.py
weatherify-0.1.1.dist-info/METADATA
weatherify-0.1.1.dist-info/WHEEL
weatherify-0.1.1.dist-info/entry_points.txt
weatherify-0.1.1.dist-info/licenses/LICENSE
weatherify-0.1.1.dist-info/RECORD
