Metadata-Version: 2.3
Name: weatherify
Version: 0.1.1
Summary: A simple weather forecasting CLI tool
Author-email: Your Name <your.email@example.com>
License-File: LICENSE
Classifier: License :: OSI Approved :: MIT License
Classifier: Operating System :: OS Independent
Classifier: Programming Language :: Python :: 3
Requires-Python: >=3.7
Requires-Dist: requests
Requires-Dist: rich
